{"success":true,"code":"SUCCESS","data":{"hoverData":{"shahid bhagat singh nagar district":{"registeredUsers":91214,"appOpens":3012229},"fazilka district":{"registeredUsers":363909,"appOpens":13937735},"barnala district":{"registeredUsers":116402,"appOpens":3446712},"mansa district":{"registeredUsers":157364,"appOpens":5338834},"ludhiana district":{"registeredUsers":1644780,"appOpens":11240356},"sri muktsar sahib district":{"registeredUsers":184238,"appOpens":8483794},"patiala district":{"registeredUsers":608884,"appOpens":9839964},"pathankot district":{"registeredUsers":214406,"appOpens":4060887},"fatehgarh sahib district":{"registeredUsers":164128,"appOpens":2748659},"rupnagar district":{"registeredUsers":183054,"appOpens":3032037},"tarn taran district":{"registeredUsers":160720,"appOpens":9780568},"sas nagar district":{"registeredUsers":904073,"appOpens":6516965},"sangrur district":{"registeredUsers":355769,"appOpens":8538887},"jalandhar district":{"registeredUsers":621327,"appOpens":6512493},"bathinda district":{"registeredUsers":420285,"appOpens":11570546},"kapurthala district":{"registeredUsers":177068,"appOpens":4865445},"firozepur district":{"registeredUsers":196883,"appOpens":7499072},"gurdaspur district":{"registeredUsers":273518,"appOpens":8368676},"amritsar district":{"registeredUsers":656700,"appOpens":9760253},"faridkot district":{"registeredUsers":136663,"appOpens":4032999},"hoshiarpur district":{"registeredUsers":303683,"appOpens":6744083},"moga district":{"registeredUsers":162514,"appOpens":5294537}}},"responseTimestamp":1669732424233}