{"success":true,"code":"SUCCESS","data":{"states":null,"districts":[{"entityName":"ranchi","metric":{"type":"TOTAL","count":94202159,"amount":1.03033639272E11}},{"entityName":"dhanbad","metric":{"type":"TOTAL","count":49235604,"amount":5.5079243334E10}},{"entityName":"hazaribag","metric":{"type":"TOTAL","count":45389162,"amount":5.5904640232E10}},{"entityName":"bokaro","metric":{"type":"TOTAL","count":42109408,"amount":4.2515426564E10}},{"entityName":"east singhbhum","metric":{"type":"TOTAL","count":40862368,"amount":4.3576468183E10}},{"entityName":"giridih","metric":{"type":"TOTAL","count":33210531,"amount":3.9664621909E10}},{"entityName":"palamu","metric":{"type":"TOTAL","count":32911720,"amount":4.077018845E10}},{"entityName":"ramgarh","metric":{"type":"TOTAL","count":22398395,"amount":2.4800047829E10}},{"entityName":"deoghar","metric":{"type":"TOTAL","count":21136954,"amount":2.3542490274E10}},{"entityName":"garhwa","metric":{"type":"TOTAL","count":19753277,"amount":2.5599337778E10}}],"pincodes":[{"entityName":"834001","metric":{"type":"TOTAL","count":31702222,"amount":3.1928362304E10}},{"entityName":"825301","metric":{"type":"TOTAL","count":10559366,"amount":1.3829749281E10}},{"entityName":"826001","metric":{"type":"TOTAL","count":10002314,"amount":1.2196018491E10}},{"entityName":"831001","metric":{"type":"TOTAL","count":7983568,"amount":8.229872519E9}},{"entityName":"827013","metric":{"type":"TOTAL","count":7790992,"amount":8.743276073E9}},{"entityName":"814112","metric":{"type":"TOTAL","count":7709230,"amount":8.899539953E9}},{"entityName":"831012","metric":{"type":"TOTAL","count":7557308,"amount":8.619491154E9}},{"entityName":"822114","metric":{"type":"TOTAL","count":7109485,"amount":9.331501263E9}},{"entityName":"834002","metric":{"type":"TOTAL","count":7053486,"amount":7.816020235E9}},{"entityName":"825303","metric":{"type":"TOTAL","count":6855207,"amount":5.162868057E9}}]},"responseTimestamp":1739974247042}