{"success":true,"code":"SUCCESS","data":{"aggregated":{"registeredUsers":19323278,"appOpens":348588666},"usersByDevice":[{"brand":"Xiaomi","count":4999610,"percentage":0.25873508625192887},{"brand":"Samsung","count":3933160,"percentage":0.20354517489216892},{"brand":"Vivo","count":3037405,"percentage":0.15718890966636198},{"brand":"Oppo","count":2144589,"percentage":0.11098474078776903},{"brand":"Realme","count":1644196,"percentage":0.08508887570732046},{"brand":"Motorola","count":402425,"percentage":0.020825917838577904},{"brand":"Lenovo","count":341420,"percentage":0.017668844799521074},{"brand":"Asus","count":291778,"percentage":0.015099818985163905},{"brand":"Huawei","count":280808,"percentage":0.01453210992462045},{"brand":"Apple","count":218506,"percentage":0.011307915768742757},{"brand":"Others","count":2029381,"percentage":0.10502260537782461}]},"responseTimestamp":1634575159969}