{"success":true,"code":"SUCCESS","data":{"hoverDataList":[{"name":"unakoti district","metric":[{"type":"TOTAL","count":991194,"amount":1.263785169E9}]},{"name":"khowai district","metric":[{"type":"TOTAL","count":645002,"amount":9.41784214E8}]},{"name":"sepahijala district","metric":[{"type":"TOTAL","count":1061392,"amount":1.753290424E9}]},{"name":"north tripura district","metric":[{"type":"TOTAL","count":2172207,"amount":3.003871219E9}]},{"name":"dhalai district","metric":[{"type":"TOTAL","count":1091481,"amount":1.552285892E9}]},{"name":"south tripura district","metric":[{"type":"TOTAL","count":1132795,"amount":1.840161769E9}]},{"name":"gomati district","metric":[{"type":"TOTAL","count":1119242,"amount":1.62876088E9}]},{"name":"west tripura district","metric":[{"type":"TOTAL","count":6187268,"amount":7.964906622E9}]}]},"responseTimestamp":1739974223846}