{"success":true,"code":"SUCCESS","data":{"hoverDataList":[{"name":"serchhip district","metric":[{"type":"TOTAL","count":11,"amount":23061.0}]},{"name":"aizawl district","metric":[{"type":"TOTAL","count":232,"amount":336391.0}]},{"name":"lunglei district","metric":[{"type":"TOTAL","count":26,"amount":36337.0}]},{"name":"mamit district","metric":[{"type":"TOTAL","count":7,"amount":17832.0}]},{"name":"lawngtlai district","metric":[{"type":"TOTAL","count":15,"amount":21225.0}]},{"name":"kolasib district","metric":[{"type":"TOTAL","count":14,"amount":33851.0}]},{"name":"champhai district","metric":[{"type":"TOTAL","count":2,"amount":112.0}]},{"name":"saiha district","metric":[{"type":"TOTAL","count":3,"amount":2497.0}]}]},"responseTimestamp":1692611303181}