{"success":true,"code":"SUCCESS","data":{"from":1561919400000,"to":1569609000000,"transactionData":[{"name":"Peer-to-peer payments","paymentInstruments":[{"type":"TOTAL","count":11775288,"amount":4.37382901199285E10}]},{"name":"Merchant payments","paymentInstruments":[{"type":"TOTAL","count":9386779,"amount":3.6156368278118167E9}]},{"name":"Recharge & bill payments","paymentInstruments":[{"type":"TOTAL","count":8289987,"amount":4.817098564823641E9}]},{"name":"Financial Services","paymentInstruments":[{"type":"TOTAL","count":61503,"amount":1.6715100880217994E7}]},{"name":"Others","paymentInstruments":[{"type":"TOTAL","count":829974,"amount":3.013785859978597E8}]}]},"responseTimestamp":1630501490922}