{"success":true,"code":"SUCCESS","data":{"aggregated":{"registeredUsers":49318,"appOpens":0},"usersByDevice":[{"brand":"Xiaomi","count":11605,"percentage":0.2353096232612839},{"brand":"Samsung","count":9972,"percentage":0.20219798045338416},{"brand":"Vivo","count":5974,"percentage":0.12113224380550712},{"brand":"Oppo","count":3608,"percentage":0.07315787339308163},{"brand":"Apple","count":2447,"percentage":0.049616772780729144},{"brand":"OnePlus","count":2409,"percentage":0.048846263027697796},{"brand":"Motorola","count":2122,"percentage":0.04302688673506631},{"brand":"Realme","count":2098,"percentage":0.04254024899630966},{"brand":"Lenovo","count":1800,"percentage":0.03649783040674804},{"brand":"Huawei","count":1766,"percentage":0.03580842694350947},{"brand":"Others","count":5517,"percentage":0.11186585019668276}]},"responseTimestamp":1630501494793}