{"success":true,"code":"SUCCESS","data":{"hoverData":{"yamunanagar district":{"registeredUsers":448397,"appOpens":11839167},"sonipat district":{"registeredUsers":828230,"appOpens":20937019},"jind district":{"registeredUsers":478669,"appOpens":19857121},"rohtak district":{"registeredUsers":570001,"appOpens":20021226},"faridabad district":{"registeredUsers":2177737,"appOpens":8207328},"mahendragarh district":{"registeredUsers":468594,"appOpens":10000716},"hisar district":{"registeredUsers":913340,"appOpens":30734384},"karnal district":{"registeredUsers":690422,"appOpens":18288840},"fatehabad district":{"registeredUsers":372881,"appOpens":18107231},"palwal district":{"registeredUsers":585232,"appOpens":6584030},"charkhi dadri district":{"registeredUsers":156148,"appOpens":5051754},"ambala district":{"registeredUsers":525599,"appOpens":7081228},"rewari district":{"registeredUsers":788131,"appOpens":9394062},"panchkula district":{"registeredUsers":380441,"appOpens":5174814},"bhiwani district":{"registeredUsers":532458,"appOpens":33189655},"sirsa district":{"registeredUsers":540767,"appOpens":29131933},"mewat district":{"registeredUsers":502900,"appOpens":8623576},"panipat district":{"registeredUsers":735266,"appOpens":13164662},"gurugram district":{"registeredUsers":3846607,"appOpens":16532850},"kaithal district":{"registeredUsers":380114,"appOpens":14849602},"kurukshetra district":{"registeredUsers":442674,"appOpens":6605291},"jhajjar district":{"registeredUsers":591881,"appOpens":14120585}}},"responseTimestamp":1697612121546}