{"success":true,"code":"SUCCESS","data":{"hoverData":{"east godavari district":{"registeredUsers":1057167,"appOpens":28275322},"srikakulam district":{"registeredUsers":437939,"appOpens":11813195},"visakhapatnam district":{"registeredUsers":1460464,"appOpens":54836001},"prakasam district":{"registeredUsers":598568,"appOpens":16267041},"anantapur district":{"registeredUsers":773656,"appOpens":22845084},"kurnool district":{"registeredUsers":755024,"appOpens":22827473},"guntur district":{"registeredUsers":1026418,"appOpens":28477132},"krishna district":{"registeredUsers":1066546,"appOpens":30077671},"spsr nellore district":{"registeredUsers":619592,"appOpens":17768733},"vizianagaram district":{"registeredUsers":394375,"appOpens":13065845},"ysr district":{"registeredUsers":574109,"appOpens":15833900},"west godavari district":{"registeredUsers":662102,"appOpens":14227407},"chittoor district":{"registeredUsers":1032733,"appOpens":34638738}}},"responseTimestamp":1630502911752}