{"success":true,"code":"SUCCESS","data":{"aggregated":{"registeredUsers":18484658,"appOpens":316991599},"usersByDevice":[{"brand":"Xiaomi","count":4888198,"percentage":0.26444622345731256},{"brand":"Samsung","count":3283813,"percentage":0.1776507306762181},{"brand":"Vivo","count":3062549,"percentage":0.16568058765274424},{"brand":"Realme","count":2443092,"percentage":0.13216863411808863},{"brand":"Oppo","count":2339620,"percentage":0.1265709108602388},{"brand":"Infinix","count":387204,"percentage":0.020947317499734105},{"brand":"Tecno","count":280644,"percentage":0.015182536782665927},{"brand":"Motorola","count":220543,"percentage":0.011931137703494432},{"brand":"Huawei","count":215004,"percentage":0.011631483795913345},{"brand":"Apple","count":158500,"percentage":0.008574678525293786},{"brand":"Others","count":1205491,"percentage":0.0652157589282961}]},"responseTimestamp":1651127666959}