{"success":true,"code":"SUCCESS","data":{"hoverDataList":[{"name":"dhamtari district","metric":[{"type":"TOTAL","count":390,"amount":722627.0}]},{"name":"korba district","metric":[{"type":"TOTAL","count":1736,"amount":2793511.0}]},{"name":"surajpur district","metric":[{"type":"TOTAL","count":416,"amount":737818.0}]},{"name":"khairagarh chhuikhadan gandai district","metric":[{"type":"TOTAL","count":116,"amount":203774.0}]},{"name":"sukma district","metric":[{"type":"TOTAL","count":126,"amount":150543.0}]},{"name":"raigarh district","metric":[{"type":"TOTAL","count":1377,"amount":1983492.0}]},{"name":"sakti district","metric":[{"type":"TOTAL","count":289,"amount":545289.0}]},{"name":"janjgir champa district","metric":[{"type":"TOTAL","count":763,"amount":1264517.0}]},{"name":"jashpur district","metric":[{"type":"TOTAL","count":326,"amount":688282.0}]},{"name":"balod district","metric":[{"type":"TOTAL","count":381,"amount":617377.0}]},{"name":"kabirdham district","metric":[{"type":"TOTAL","count":264,"amount":379717.0}]},{"name":"balodabazar bhatapara district","metric":[{"type":"TOTAL","count":566,"amount":751821.0}]},{"name":"surguja district","metric":[{"type":"TOTAL","count":608,"amount":1284497.0}]},{"name":"mohla manpur ambagarh chouki district","metric":[{"type":"TOTAL","count":103,"amount":212905.0}]},{"name":"dantewada district","metric":[{"type":"TOTAL","count":272,"amount":465493.0}]},{"name":"durg district","metric":[{"type":"TOTAL","count":3059,"amount":5223646.0}]},{"name":"gaurela pendra marwahi district","metric":[{"type":"TOTAL","count":132,"amount":149779.0}]},{"name":"gariaband district","metric":[{"type":"TOTAL","count":215,"amount":288201.0}]},{"name":"rajnandgaon district","metric":[{"type":"TOTAL","count":540,"amount":929044.0}]},{"name":"manendragarh chirmiri bharatpur district","metric":[{"type":"TOTAL","count":255,"amount":464127.0}]},{"name":"balrampur ramanujganj district","metric":[{"type":"TOTAL","count":277,"amount":505829.0}]},{"name":"raipur district","metric":[{"type":"TOTAL","count":5081,"amount":8313161.0}]},{"name":"narayanpur district","metric":[{"type":"TOTAL","count":111,"amount":215593.0}]},{"name":"korea district","metric":[{"type":"TOTAL","count":188,"amount":333787.0}]},{"name":"mungeli district","metric":[{"type":"TOTAL","count":188,"amount":244662.0}]},{"name":"bilaspur district","metric":[{"type":"TOTAL","count":2244,"amount":3412964.0}]},{"name":"bijapur district","metric":[{"type":"TOTAL","count":161,"amount":236137.0}]},{"name":"bemetara district","metric":[{"type":"TOTAL","count":316,"amount":477664.0}]},{"name":"north bastar kanker district","metric":[{"type":"TOTAL","count":432,"amount":985597.0}]},{"name":"sarangarh bilaigarh district","metric":[{"type":"TOTAL","count":230,"amount":287919.0}]},{"name":"bastar district","metric":[{"type":"TOTAL","count":769,"amount":1263838.0}]},{"name":"kondagaon district","metric":[{"type":"TOTAL","count":302,"amount":467088.0}]},{"name":"mahasamund district","metric":[{"type":"TOTAL","count":490,"amount":820466.0}]}]},"responseTimestamp":1739974644831}