{"success":true,"code":"SUCCESS","data":{"states":null,"districts":[{"name":"jaipur","registeredUsers":5219354},{"name":"jaipur rural","registeredUsers":1430124},{"name":"kota","registeredUsers":1348463},{"name":"sikar","registeredUsers":1185364},{"name":"jodhpur","registeredUsers":1154160},{"name":"udaipur","registeredUsers":1145180},{"name":"bikaner","registeredUsers":1138132},{"name":"alwar","registeredUsers":1057687},{"name":"ajmer","registeredUsers":1011766},{"name":"bhilwara","registeredUsers":934621}],"pincodes":[{"name":"302012","registeredUsers":590885},{"name":"302029","registeredUsers":429792},{"name":"313001","registeredUsers":407874},{"name":"301001","registeredUsers":395851},{"name":"334001","registeredUsers":382863},{"name":"302020","registeredUsers":373776},{"name":"311001","registeredUsers":357727},{"name":"324005","registeredUsers":317684},{"name":"302017","registeredUsers":309145},{"name":"332001","registeredUsers":306609}]},"responseTimestamp":1739974317225}