{"success":true,"code":"SUCCESS","data":{"states":null,"districts":[{"entityName":"dadra and nagar haveli","metric":{"type":"TOTAL","count":1178976,"amount":1.6834800216173902E9}},{"entityName":"daman","metric":{"type":"TOTAL","count":596994,"amount":9.213728764402872E8}},{"entityName":"diu","metric":{"type":"TOTAL","count":41821,"amount":9.565820277082601E7}}],"pincodes":[{"entityName":"396230","metric":{"type":"TOTAL","count":983398,"amount":1.3746326008369546E9}},{"entityName":"396210","metric":{"type":"TOTAL","count":386879,"amount":6.144981583519889E8}},{"entityName":"396215","metric":{"type":"TOTAL","count":203349,"amount":2.9814487150685096E8}},{"entityName":"396235","metric":{"type":"TOTAL","count":195578,"amount":3.088474207804359E8}},{"entityName":"362520","metric":{"type":"TOTAL","count":23557,"amount":5.1879988881247215E7}},{"entityName":"362571","metric":{"type":"TOTAL","count":12306,"amount":3.314015679102123E7}},{"entityName":"396220","metric":{"type":"TOTAL","count":6766,"amount":8729846.58144759}},{"entityName":"362540","metric":{"type":"TOTAL","count":5159,"amount":9482020.154901681}},{"entityName":"362570","metric":{"type":"TOTAL","count":799,"amount":1156036.9436559002}}]},"responseTimestamp":1630501493336}