{"success":true,"code":"SUCCESS","data":{"states":null,"districts":[{"entityName":"chandigarh","metric":{"type":"TOTAL","count":2158086,"amount":5.08980935336507E9}}],"pincodes":[{"entityName":"160008","metric":{"type":"TOTAL","count":813514,"amount":2.456075017244974E9}},{"entityName":"160101","metric":{"type":"TOTAL","count":187085,"amount":3.47310967735443E8}},{"entityName":"160036","metric":{"type":"TOTAL","count":164223,"amount":3.219610210310574E8}},{"entityName":"160002","metric":{"type":"TOTAL","count":164083,"amount":3.2385918860292995E8}},{"entityName":"160047","metric":{"type":"TOTAL","count":126033,"amount":2.6289121826635933E8}},{"entityName":"160022","metric":{"type":"TOTAL","count":100215,"amount":2.1247391786900696E8}},{"entityName":"160014","metric":{"type":"TOTAL","count":89228,"amount":1.442377809553475E8}},{"entityName":"160015","metric":{"type":"TOTAL","count":57169,"amount":8.861510882699049E7}},{"entityName":"160030","metric":{"type":"TOTAL","count":52790,"amount":1.1292529067615485E8}},{"entityName":"160019","metric":{"type":"TOTAL","count":52423,"amount":1.1448757678222746E8}}]},"responseTimestamp":1630501492698}