{"success":true,"code":"SUCCESS","data":{"hoverDataList":[{"name":"dhamtari district","metric":[{"type":"TOTAL","count":624812,"amount":1.1166300060085955E9}]},{"name":"korba district","metric":[{"type":"TOTAL","count":1984429,"amount":3.1849434283822093E9}]},{"name":"surajpur district","metric":[{"type":"TOTAL","count":676567,"amount":1.3057890554768894E9}]},{"name":"baloda bazar district","metric":[{"type":"TOTAL","count":1079166,"amount":1.896871501902258E9}]},{"name":"sukma district","metric":[{"type":"TOTAL","count":238465,"amount":6.385244907419174E8}]},{"name":"raigarh district","metric":[{"type":"TOTAL","count":2064164,"amount":3.6377254808909154E9}]},{"name":"janjgir champa district","metric":[{"type":"TOTAL","count":2192318,"amount":3.743676244613643E9}]},{"name":"jashpur district","metric":[{"type":"TOTAL","count":599900,"amount":1.1011790488851104E9}]},{"name":"balod district","metric":[{"type":"TOTAL","count":653978,"amount":1.0653146125838513E9}]},{"name":"kabirdham district","metric":[{"type":"TOTAL","count":551734,"amount":8.945824814049557E8}]},{"name":"surguja district","metric":[{"type":"TOTAL","count":1086420,"amount":2.0646534037490907E9}]},{"name":"dantewada district","metric":[{"type":"TOTAL","count":318775,"amount":7.899819555130013E8}]},{"name":"gariyaband district","metric":[{"type":"TOTAL","count":417169,"amount":7.39494892833446E8}]},{"name":"durg district","metric":[{"type":"TOTAL","count":4913427,"amount":7.302773368858854E9}]},{"name":"rajnandgaon district","metric":[{"type":"TOTAL","count":1290120,"amount":2.254466252901078E9}]},{"name":"raipur district","metric":[{"type":"TOTAL","count":8570997,"amount":1.4747848599148956E10}]},{"name":"narayanpur district","metric":[{"type":"TOTAL","count":126331,"amount":2.571674675268439E8}]},{"name":"kanker district","metric":[{"type":"TOTAL","count":634514,"amount":1.3588498048078868E9}]},{"name":"korea district","metric":[{"type":"TOTAL","count":754942,"amount":1.3951669617705023E9}]},{"name":"mungeli district","metric":[{"type":"TOTAL","count":363678,"amount":6.660874222678833E8}]},{"name":"bilaspur district","metric":[{"type":"TOTAL","count":2837963,"amount":4.82926031692908E9}]},{"name":"balrampur district","metric":[{"type":"TOTAL","count":578790,"amount":1.3403688494000525E9}]},{"name":"bijapur district","metric":[{"type":"TOTAL","count":307460,"amount":7.668980118716979E8}]},{"name":"bemetara district","metric":[{"type":"TOTAL","count":520944,"amount":8.701516781162208E8}]},{"name":"bastar district","metric":[{"type":"TOTAL","count":738632,"amount":1.5664152590535295E9}]},{"name":"kondagaon district","metric":[{"type":"TOTAL","count":369192,"amount":7.289296480722761E8}]},{"name":"mahasamund district","metric":[{"type":"TOTAL","count":1034749,"amount":1.9512240402379332E9}]}]},"responseTimestamp":1630502911378}