{"success":true,"code":"SUCCESS","data":{"states":null,"districts":[{"entityName":"aizawl","metric":{"type":"TOTAL","count":360350,"amount":1.0543416988459929E9}},{"entityName":"lunglei","metric":{"type":"TOTAL","count":99571,"amount":2.751643847691406E8}},{"entityName":"lawngtlai","metric":{"type":"TOTAL","count":60120,"amount":1.763224954134693E8}},{"entityName":"kolasib","metric":{"type":"TOTAL","count":55854,"amount":1.570462323046887E8}},{"entityName":"mamit","metric":{"type":"TOTAL","count":39889,"amount":1.1149021309424147E8}},{"entityName":"champhai","metric":{"type":"TOTAL","count":33252,"amount":1.1007344044820768E8}},{"entityName":"serchhip","metric":{"type":"TOTAL","count":25172,"amount":7.143198254694104E7}},{"entityName":"saiha","metric":{"type":"TOTAL","count":19566,"amount":8.204063784033793E7}}],"pincodes":[{"entityName":"796009","metric":{"type":"TOTAL","count":78140,"amount":2.4156843565820393E8}},{"entityName":"796008","metric":{"type":"TOTAL","count":73739,"amount":2.1106610319186488E8}},{"entityName":"796005","metric":{"type":"TOTAL","count":70513,"amount":2.0449073648261383E8}},{"entityName":"796701","metric":{"type":"TOTAL","count":57742,"amount":1.6097513003242403E8}},{"entityName":"796017","metric":{"type":"TOTAL","count":40048,"amount":1.1770840460364096E8}},{"entityName":"796012","metric":{"type":"TOTAL","count":28226,"amount":8.855858660795963E7}},{"entityName":"796014","metric":{"type":"TOTAL","count":26300,"amount":7.810406520237857E7}},{"entityName":"796772","metric":{"type":"TOTAL","count":25913,"amount":6.520630327308114E7}},{"entityName":"796081","metric":{"type":"TOTAL","count":19874,"amount":5.722471590311567E7}},{"entityName":"796181","metric":{"type":"TOTAL","count":17158,"amount":5.0769743525687404E7}}]},"responseTimestamp":1674558261524}