{"success":true,"code":"SUCCESS","data":{"states":null,"districts":[{"entityName":"dadra and nagar haveli","metric":{"type":"TOTAL","count":128642,"amount":1.869268425467928E8}},{"entityName":"daman","metric":{"type":"TOTAL","count":67705,"amount":1.0440732193224815E8}},{"entityName":"diu","metric":{"type":"TOTAL","count":6279,"amount":1.0736607177110624E7}}],"pincodes":[{"entityName":"396230","metric":{"type":"TOTAL","count":107488,"amount":1.581759378700928E8}},{"entityName":"396210","metric":{"type":"TOTAL","count":42931,"amount":7.241409631243189E7}},{"entityName":"396215","metric":{"type":"TOTAL","count":24403,"amount":3.1388224686525453E7}},{"entityName":"396235","metric":{"type":"TOTAL","count":21154,"amount":2.875090467670025E7}},{"entityName":"362520","metric":{"type":"TOTAL","count":3563,"amount":6593600.730532296}},{"entityName":"362571","metric":{"type":"TOTAL","count":1690,"amount":2467269.461487418}},{"entityName":"362540","metric":{"type":"TOTAL","count":881,"amount":1471603.4288316348}},{"entityName":"396220","metric":{"type":"TOTAL","count":371,"amount":605000.9332907782}},{"entityName":"362570","metric":{"type":"TOTAL","count":145,"amount":204133.5562592716}}]},"responseTimestamp":1630501487612}