{"success":true,"code":"SUCCESS","data":{"states":null,"districts":[{"entityName":"gautambuddha nagar","metric":{"type":"TOTAL","count":10577,"amount":1.7321952E7}},{"entityName":"ghaziabad","metric":{"type":"TOTAL","count":9193,"amount":1.400078E7}},{"entityName":"lucknow","metric":{"type":"TOTAL","count":6514,"amount":1.1848066E7}},{"entityName":"kanpur nagar","metric":{"type":"TOTAL","count":4825,"amount":7438114.0}},{"entityName":"meerut","metric":{"type":"TOTAL","count":4013,"amount":6718841.0}},{"entityName":"prayagraj","metric":{"type":"TOTAL","count":3439,"amount":5704952.0}},{"entityName":"gorakhpur","metric":{"type":"TOTAL","count":2752,"amount":4772281.0}},{"entityName":"moradabad","metric":{"type":"TOTAL","count":2648,"amount":4074503.0}},{"entityName":"agra","metric":{"type":"TOTAL","count":2490,"amount":4578823.0}},{"entityName":"varanasi","metric":{"type":"TOTAL","count":2311,"amount":4039502.0}}],"pincodes":[{"entityName":"201301","metric":{"type":"TOTAL","count":2329,"amount":3345795.0}},{"entityName":"201009","metric":{"type":"TOTAL","count":1769,"amount":2554328.0}},{"entityName":"244001","metric":{"type":"TOTAL","count":1637,"amount":2429001.0}},{"entityName":"201318","metric":{"type":"TOTAL","count":1618,"amount":2803537.0}},{"entityName":"250001","metric":{"type":"TOTAL","count":1273,"amount":2110213.0}},{"entityName":"201102","metric":{"type":"TOTAL","count":1269,"amount":1704847.0}},{"entityName":"201307","metric":{"type":"TOTAL","count":995,"amount":1815161.0}},{"entityName":"201303","metric":{"type":"TOTAL","count":831,"amount":1312276.0}},{"entityName":"247001","metric":{"type":"TOTAL","count":799,"amount":1604933.0}},{"entityName":"250002","metric":{"type":"TOTAL","count":797,"amount":1238183.0}}]},"responseTimestamp":1739974368486}