{"success":true,"code":"SUCCESS","data":{"states":null,"districts":[{"entityName":"puducherry","metric":{"type":"TOTAL","count":1515874,"amount":3.1442321516990056E9}},{"entityName":"yanam","metric":{"type":"TOTAL","count":105613,"amount":2.1235048731674817E8}},{"entityName":"karaikal","metric":{"type":"TOTAL","count":85556,"amount":2.017964439712459E8}},{"entityName":"mahe","metric":{"type":"TOTAL","count":23859,"amount":3.9701146447601184E7}}],"pincodes":[{"entityName":"605002","metric":{"type":"TOTAL","count":563408,"amount":1.4636057265866117E9}},{"entityName":"605110","metric":{"type":"TOTAL","count":130756,"amount":2.3126511234255123E8}},{"entityName":"533464","metric":{"type":"TOTAL","count":105613,"amount":2.1235048731674814E8}},{"entityName":"605008","metric":{"type":"TOTAL","count":96375,"amount":1.7085250730649185E8}},{"entityName":"605004","metric":{"type":"TOTAL","count":93247,"amount":1.7420821703337535E8}},{"entityName":"605107","metric":{"type":"TOTAL","count":91162,"amount":1.5656587989717433E8}},{"entityName":"605009","metric":{"type":"TOTAL","count":86795,"amount":1.579993163035466E8}},{"entityName":"605011","metric":{"type":"TOTAL","count":62198,"amount":1.2485034092547211E8}},{"entityName":"605010","metric":{"type":"TOTAL","count":61273,"amount":1.0542447256759906E8}},{"entityName":"605013","metric":{"type":"TOTAL","count":56558,"amount":1.0533061675937249E8}}]},"responseTimestamp":1630501493095}