{"success":true,"code":"SUCCESS","data":{"states":null,"districts":[{"name":"indore","registeredUsers":1769869},{"name":"bhopal","registeredUsers":1340741},{"name":"gwalior","registeredUsers":703232},{"name":"jabalpur","registeredUsers":650087},{"name":"ujjain","registeredUsers":513868},{"name":"sagar","registeredUsers":432938},{"name":"dhar","registeredUsers":415117},{"name":"rewa","registeredUsers":403013},{"name":"chhindwara","registeredUsers":399276},{"name":"satna","registeredUsers":368299}],"pincodes":[{"name":"482002","registeredUsers":202915},{"name":"452001","registeredUsers":185582},{"name":"455001","registeredUsers":180488},{"name":"452010","registeredUsers":171754},{"name":"462001","registeredUsers":149137},{"name":"457001","registeredUsers":145248},{"name":"482001","registeredUsers":138100},{"name":"480001","registeredUsers":134163},{"name":"474001","registeredUsers":125599},{"name":"485001","registeredUsers":125104}]},"responseTimestamp":1630501499917}