{"success":true,"code":"SUCCESS","data":{"from":1704047400000,"to":1711564200000,"transactionData":[{"name":"Peer-to-peer payments","paymentInstruments":[{"type":"TOTAL","count":852682,"amount":2.946283349E9}]},{"name":"Merchant payments","paymentInstruments":[{"type":"TOTAL","count":537550,"amount":5.68411807E8}]},{"name":"Recharge & bill payments","paymentInstruments":[{"type":"TOTAL","count":233738,"amount":1.09792002E8}]},{"name":"Financial Services","paymentInstruments":[{"type":"TOTAL","count":1756,"amount":4788439.0}]},{"name":"Others","paymentInstruments":[{"type":"TOTAL","count":1290,"amount":821133.0}]}]},"responseTimestamp":1714727636462}