{"success":true,"code":"SUCCESS","data":{"hoverDataList":[{"name":"serchhip district","metric":[{"type":"TOTAL","count":2,"amount":811.0}]},{"name":"aizawl district","metric":[{"type":"TOTAL","count":149,"amount":105527.0}]},{"name":"lunglei district","metric":[{"type":"TOTAL","count":9,"amount":2272.0}]},{"name":"mamit district","metric":[{"type":"TOTAL","count":4,"amount":6121.0}]},{"name":"lawngtlai district","metric":[{"type":"TOTAL","count":9,"amount":1913.0}]},{"name":"kolasib district","metric":[{"type":"TOTAL","count":4,"amount":188.0}]},{"name":"champhai district","metric":[{"type":"TOTAL","count":8,"amount":2921.0}]},{"name":"saiha district","metric":[{"type":"TOTAL","count":2,"amount":5052.0}]}]},"responseTimestamp":1692611045373}