{"success":true,"code":"SUCCESS","data":{"states":null,"districts":[{"name":"west tripura","registeredUsers":315337},{"name":"sepahijala","registeredUsers":87910},{"name":"south tripura","registeredUsers":87397},{"name":"north tripura","registeredUsers":81280},{"name":"gomati","registeredUsers":74242},{"name":"dhalai","registeredUsers":64896},{"name":"khowai","registeredUsers":50673},{"name":"unakoti","registeredUsers":44609}],"pincodes":[{"name":"799001","registeredUsers":53590},{"name":"799003","registeredUsers":43963},{"name":"799006","registeredUsers":27509},{"name":"799102","registeredUsers":25835},{"name":"799114","registeredUsers":23792},{"name":"799002","registeredUsers":23365},{"name":"799004","registeredUsers":23095},{"name":"799155","registeredUsers":21559},{"name":"799007","registeredUsers":20080},{"name":"799205","registeredUsers":19663}]},"responseTimestamp":1706092768878}