{"success":true,"code":"SUCCESS","data":{"hoverData":{"yamunanagar district":{"registeredUsers":500980,"appOpens":18128599},"sonipat district":{"registeredUsers":1056983,"appOpens":39330457},"jind district":{"registeredUsers":495065,"appOpens":39535532},"rohtak district":{"registeredUsers":639086,"appOpens":36347617},"faridabad district":{"registeredUsers":2263356,"appOpens":16550260},"mahendragarh district":{"registeredUsers":472734,"appOpens":18622010},"hisar district":{"registeredUsers":926328,"appOpens":54255144},"karnal district":{"registeredUsers":740449,"appOpens":40853590},"fatehabad district":{"registeredUsers":381846,"appOpens":26884675},"palwal district":{"registeredUsers":643422,"appOpens":97630527},"charkhi dadri district":{"registeredUsers":222105,"appOpens":21505894},"ambala district":{"registeredUsers":528044,"appOpens":9678650},"rewari district":{"registeredUsers":817240,"appOpens":9024136},"panchkula district":{"registeredUsers":383609,"appOpens":12986620},"bhiwani district":{"registeredUsers":527698,"appOpens":40345768},"sirsa district":{"registeredUsers":545573,"appOpens":66169554},"panipat district":{"registeredUsers":885898,"appOpens":34245832},"nuh district":{"registeredUsers":657942,"appOpens":26240514},"gurugram district":{"registeredUsers":4264705,"appOpens":36728292},"kaithal district":{"registeredUsers":394536,"appOpens":32169593},"kurukshetra district":{"registeredUsers":452759,"appOpens":11064507},"jhajjar district":{"registeredUsers":726930,"appOpens":13292042}}},"responseTimestamp":1739974315519}