{"success":true,"code":"SUCCESS","data":{"states":null,"districts":[{"name":"dimapur","registeredUsers":53696},{"name":"kohima","registeredUsers":20644},{"name":"mokokchung","registeredUsers":7626},{"name":"mon","registeredUsers":5747},{"name":"wokha","registeredUsers":4118},{"name":"phek","registeredUsers":3637},{"name":"tuensang","registeredUsers":3634},{"name":"zunheboto","registeredUsers":2898},{"name":"peren","registeredUsers":1899},{"name":"kiphire","registeredUsers":1814}],"pincodes":[{"name":"797112","registeredUsers":20343},{"name":"797115","registeredUsers":7928},{"name":"797001","registeredUsers":7238},{"name":"797103","registeredUsers":6476},{"name":"797113","registeredUsers":6010},{"name":"798601","registeredUsers":4927},{"name":"797120","registeredUsers":4924},{"name":"797117","registeredUsers":3793},{"name":"797118","registeredUsers":3712},{"name":"797111","registeredUsers":3534}]},"responseTimestamp":1630501498435}