{"success":true,"code":"SUCCESS","data":{"states":null,"districts":[{"name":"kamrup metropolitan","registeredUsers":589688},{"name":"nagaon","registeredUsers":200243},{"name":"barpeta","registeredUsers":177789},{"name":"cachar","registeredUsers":172056},{"name":"sonitpur","registeredUsers":158555},{"name":"dibrugarh","registeredUsers":158509},{"name":"kamrup","registeredUsers":147671},{"name":"tinsukia","registeredUsers":134067},{"name":"jorhat","registeredUsers":116616},{"name":"dhubri","registeredUsers":101643}],"pincodes":[{"name":"781032","registeredUsers":46783},{"name":"781022","registeredUsers":37652},{"name":"781001","registeredUsers":34483},{"name":"781038","registeredUsers":30260},{"name":"783380","registeredUsers":29414},{"name":"781011","registeredUsers":28064},{"name":"785001","registeredUsers":27259},{"name":"786001","registeredUsers":26762},{"name":"781028","registeredUsers":24813},{"name":"782435","registeredUsers":24658}]},"responseTimestamp":1630501499752}