{"success":true,"code":"SUCCESS","data":{"hoverDataList":[{"name":"morena district","metric":[{"type":"TOTAL","count":351,"amount":428881.0}]},{"name":"alirajpur district","metric":[{"type":"TOTAL","count":88,"amount":185148.0}]},{"name":"sehore district","metric":[{"type":"TOTAL","count":448,"amount":819074.0}]},{"name":"rajgarh district","metric":[{"type":"TOTAL","count":257,"amount":367678.0}]},{"name":"khargone district","metric":[{"type":"TOTAL","count":376,"amount":619882.0}]},{"name":"satna district","metric":[{"type":"TOTAL","count":682,"amount":1048846.0}]},{"name":"narsinghpur district","metric":[{"type":"TOTAL","count":238,"amount":439141.0}]},{"name":"jabalpur district","metric":[{"type":"TOTAL","count":1596,"amount":2667756.0}]},{"name":"hoshangabad district","metric":[{"type":"TOTAL","count":398,"amount":810481.0}]},{"name":"vidisha district","metric":[{"type":"TOTAL","count":269,"amount":489111.0}]},{"name":"balaghat district","metric":[{"type":"TOTAL","count":399,"amount":739112.0}]},{"name":"singrauli district","metric":[{"type":"TOTAL","count":786,"amount":1315955.0}]},{"name":"betul district","metric":[{"type":"TOTAL","count":444,"amount":628222.0}]},{"name":"sidhi district","metric":[{"type":"TOTAL","count":248,"amount":296190.0}]},{"name":"datia district","metric":[{"type":"TOTAL","count":144,"amount":232374.0}]},{"name":"dewas district","metric":[{"type":"TOTAL","count":641,"amount":1082104.0}]},{"name":"sheopur district","metric":[{"type":"TOTAL","count":88,"amount":194312.0}]},{"name":"neemuch district","metric":[{"type":"TOTAL","count":250,"amount":407496.0}]},{"name":"raisen district","metric":[{"type":"TOTAL","count":328,"amount":602318.0}]},{"name":"mandsaur district","metric":[{"type":"TOTAL","count":313,"amount":417610.0}]},{"name":"barwani district","metric":[{"type":"TOTAL","count":219,"amount":331867.0}]},{"name":"katni district","metric":[{"type":"TOTAL","count":431,"amount":574680.0}]},{"name":"dindori district","metric":[{"type":"TOTAL","count":116,"amount":228380.0}]},{"name":"shivpuri district","metric":[{"type":"TOTAL","count":249,"amount":338922.0}]},{"name":"gwalior district","metric":[{"type":"TOTAL","count":2069,"amount":2813452.0}]},{"name":"anuppur district","metric":[{"type":"TOTAL","count":248,"amount":392416.0}]},{"name":"agar malwa district","metric":[{"type":"TOTAL","count":100,"amount":193707.0}]},{"name":"ashoknagar district","metric":[{"type":"TOTAL","count":92,"amount":137168.0}]},{"name":"sagar district","metric":[{"type":"TOTAL","count":727,"amount":1199223.0}]},{"name":"niwari district","metric":[{"type":"TOTAL","count":87,"amount":207354.0}]},{"name":"rewa district","metric":[{"type":"TOTAL","count":789,"amount":1121774.0}]},{"name":"shajapur district","metric":[{"type":"TOTAL","count":236,"amount":420853.0}]},{"name":"ujjain district","metric":[{"type":"TOTAL","count":970,"amount":1468543.0}]},{"name":"bhind district","metric":[{"type":"TOTAL","count":244,"amount":424433.0}]},{"name":"tikamgarh district","metric":[{"type":"TOTAL","count":130,"amount":269606.0}]},{"name":"seoni district","metric":[{"type":"TOTAL","count":325,"amount":658463.0}]},{"name":"harda district","metric":[{"type":"TOTAL","count":158,"amount":320633.0}]},{"name":"burhanpur district","metric":[{"type":"TOTAL","count":127,"amount":216580.0}]},{"name":"damoh district","metric":[{"type":"TOTAL","count":159,"amount":247992.0}]},{"name":"bhopal district","metric":[{"type":"TOTAL","count":3313,"amount":6161923.0}]},{"name":"jhabua district","metric":[{"type":"TOTAL","count":226,"amount":280922.0}]},{"name":"dhar district","metric":[{"type":"TOTAL","count":737,"amount":1069689.0}]},{"name":"guna district","metric":[{"type":"TOTAL","count":315,"amount":380891.0}]},{"name":"east nimar district","metric":[{"type":"TOTAL","count":305,"amount":563893.0}]},{"name":"chhindwara district","metric":[{"type":"TOTAL","count":667,"amount":1068226.0}]},{"name":"umaria district","metric":[{"type":"TOTAL","count":105,"amount":124526.0}]},{"name":"mandla district","metric":[{"type":"TOTAL","count":231,"amount":294123.0}]},{"name":"indore district","metric":[{"type":"TOTAL","count":6387,"amount":9795734.0}]},{"name":"shahdol district","metric":[{"type":"TOTAL","count":278,"amount":458453.0}]},{"name":"ratlam district","metric":[{"type":"TOTAL","count":454,"amount":664200.0}]},{"name":"panna district","metric":[{"type":"TOTAL","count":136,"amount":215079.0}]},{"name":"chhatarpur district","metric":[{"type":"TOTAL","count":326,"amount":527952.0}]}]},"responseTimestamp":1697612175151}